gcs_utils/__init__.py
gcs_utils/client.py
zionclouds_common_code-1.0.1.dist-info/METADATA
zionclouds_common_code-1.0.1.dist-info/WHEEL
zionclouds_common_code-1.0.1.dist-info/top_level.txt
zionclouds_common_code-1.0.1.dist-info/RECORD
