Metadata-Version: 2.4
Name: ZionClouds-Common-code
Version: 1.0.1
Summary: A simple utility library for common operations used in ZionClouds projects
Home-page: https://github.com/ZionClouds/ZionClouds.git
Author: Harshith Gundela
Author-email: harshith.gundela@zionclouds.com
Classifier: Development Status :: 3 - Alpha
Classifier: Intended Audience :: Developers
Classifier: License :: OSI Approved :: MIT License
Classifier: Operating System :: OS Independent
Classifier: Programming Language :: Python :: 3
Classifier: Programming Language :: Python :: 3.7
Classifier: Programming Language :: Python :: 3.8
Classifier: Programming Language :: Python :: 3.9
Classifier: Programming Language :: Python :: 3.10
Requires-Python: >=3.10
Requires-Dist: google-cloud-storage>=2.0.0
Dynamic: author
Dynamic: author-email
Dynamic: classifier
Dynamic: description
Dynamic: description-content-type
Dynamic: home-page
Dynamic: requires-dist
Dynamic: requires-python
Dynamic: summary
